am2320_driver/__init__.py
am2320_driver/am2320.py
am2320_driver-0.1.2.dist-info/LICENSE
am2320_driver-0.1.2.dist-info/WHEEL
am2320_driver-0.1.2.dist-info/METADATA
am2320_driver-0.1.2.dist-info/RECORD
