Metadata-Version: 2.1
Name: am2320-driver
Version: 0.1.2
Summary: This is pip package for using AM2320 Digital Temperature and Humidity Sensor.
Home-page: https://github.com/chanyou0311/am2320-driver-py
License: MIT
Author: chanyou0311
Author-email: chanyou0311@gmail.com
Requires-Python: >=3.8,<4.0
Classifier: License :: OSI Approved :: MIT License
Classifier: Programming Language :: Python :: 3
Classifier: Programming Language :: Python :: 3.10
Classifier: Programming Language :: Python :: 3.8
Classifier: Programming Language :: Python :: 3.9
Requires-Dist: smbus2 (>=0.4.1,<0.5.0)
Project-URL: Repository, https://github.com/chanyou0311/am2320-driver-py
